loopkey_client/__init__.py
loopkey_client/access_group.py
loopkey_client/booking.py
loopkey_client/client.py
loopkey_client/const.py
loopkey_client/corporate_door.py
loopkey_client/corporation.py
loopkey_client/exceptions.py
loopkey_client/gateway.py
loopkey_client/loopkey_api.py
loopkey_client/regular_door.py
loopkey_client/role.py
loopkey_client/site.py
pyloopkey-0.1.5.dist-info/METADATA
pyloopkey-0.1.5.dist-info/WHEEL
pyloopkey-0.1.5.dist-info/top_level.txt
pyloopkey-0.1.5.dist-info/RECORD
