Metadata-Version: 2.1
Name: pyloopkey
Version: 0.1.5
Summary: Loopkey API library
Home-page: https://github.com/casai-org/pyloopkey
Author: Mauricio Cisneros
Author-email: mauricio.cisneros@casai.com
License: UNKNOWN
Platform: UNKNOWN
Requires-Dist: requests (>=2.20.0)
